arabic_reshaper/__init__.py
arabic_reshaper/__version__.py
arabic_reshaper/arabic_reshaper.py
arabic_reshaper/letters.py
arabic_reshaper/ligatures.py
arabic_reshaper/reshaper_config.py
arabic_reshaper-2.1.4.dist-info/LICENSE
arabic_reshaper-2.1.4.dist-info/METADATA
arabic_reshaper-2.1.4.dist-info/WHEEL
arabic_reshaper-2.1.4.dist-info/top_level.txt
arabic_reshaper-2.1.4.dist-info/RECORD
